main.py
test_uv_demo_package_install-0.2.0.dist-info/METADATA
test_uv_demo_package_install-0.2.0.dist-info/WHEEL
test_uv_demo_package_install-0.2.0.dist-info/top_level.txt
test_uv_demo_package_install-0.2.0.dist-info/RECORD
