Metadata-Version: 2.4
Name: test-uv-demo-package-install
Version: 0.2.0
Summary: Add your description here
Requires-Python: >=3.13
Requires-Dist: ipykernel>=7.0.0
Requires-Dist: is-uv-demo>=0.1.0
